CHANGELOG.md
LICENSE
MANIFEST.in
README.rst
setup.cfg
setup.py
django_teledex/__init__.py
django_teledex/admin.py
django_teledex/apps.py
django_teledex/choices.py
django_teledex/fields.py
django_teledex/models.py
django_teledex.egg-info/PKG-INFO
django_teledex.egg-info/SOURCES.txt
django_teledex.egg-info/dependency_links.txt
django_teledex.egg-info/not-zip-safe
django_teledex.egg-info/requires.txt
django_teledex.egg-info/top_level.txt
django_teledex/migrations/0001_initial.py
django_teledex/migrations/__init__.py
django_teledex/tests/__init__.py
django_teledex/tests/test_fields.py
django_teledex/tests/test_models.py
django_teledex/tests/testapp/__init__.py
django_teledex/tests/testapp/models.py
django_teledex/tests/testapp/settings.py
docs/Makefile
docs/conf.py
docs/developer.rst
docs/index.rst
docs/installation.rst
docs/usage.rst
docs/_build/doctrees/developer.doctree
docs/_build/doctrees/environment.pickle
docs/_build/doctrees/index.doctree
docs/_build/doctrees/installation.doctree
docs/_build/doctrees/usage.doctree
docs/_build/doctrees/internals/reference/django_teledex.choices.doctree
docs/_build/doctrees/internals/reference/django_teledex.fields.doctree
docs/_build/doctrees/internals/reference/django_teledex.models.doctree
docs/_build/doctrees/internals/reference/index.doctree
docs/_build/html/.buildinfo
docs/_build/html/developer.html
docs/_build/html/genindex.html
docs/_build/html/index.html
docs/_build/html/installation.html
docs/_build/html/objects.inv
docs/_build/html/py-modindex.html
docs/_build/html/search.html
docs/_build/html/searchindex.js
docs/_build/html/usage.html
docs/_build/html/_modules/index.html
docs/_build/html/_modules/django/contrib/contenttypes/fields.html
docs/_build/html/_modules/django/db/models/manager.html
docs/_build/html/_modules/django/db/models/fields/related.html
docs/_build/html/_modules/django/utils/functional.html
docs/_build/html/_modules/django_countries/fields.html
docs/_build/html/_modules/django_teledex/fields.html
docs/_build/html/_modules/django_teledex/models.html
docs/_build/html/_modules/phonenumber_field/modelfields.html
docs/_build/html/_sources/developer.txt
docs/_build/html/_sources/index.txt
